[
    {
        "name": "basic tower",
        "spriteSheetNum": 0,
        "displayInfo": {
            "Ammo": "standard",
            "Damage": "low",
            "Rate": "medium",
            "Range": "medium",
            "Resistance": "none"
        },
        "gameData": {
            "seekRange": 5,
            "shootRange": 8,
            "damage": 5,
            "rateOfFire": 60,
            "bulletSpeed": 8,
            "bulletType": "simple",
            "numberOfBullets": 1,
            "turns": true,
            "piercing": false
        }
    },
    {
        "name": "all direction tower",
        "spriteSheetNum": 1,
        "displayInfo": {
            "Ammo": "all dirs",
            "Damage": "low",
            "Rate": "medium",
            "Range": "short",
            "Resistance": "none"
        },
        "gameData": {
            "seekRange": 1.6,
            "shootRange": 1.6,
            "damage": 5,
            "rateOfFire": 45,
            "bulletSpeed": 5,
            "bulletType": "simple",
            "numberOfBullets": 8,
            "turns": false,
            "piercing": false
        }
    },
    {
        "name": "triple tower",
        "spriteSheetNum": 2,
        "displayInfo": {
            "Ammo": "3 standard",
            "Damage": "medium",
            "Rate": "medium",
            "Range": "medium",
            "Resistance": "none"
        },
        "gameData": {
            "seekRange": 5,
            "shootRange": 8,
            "damage": 5,
            "rateOfFire": 60,
            "bulletSpeed": 8,
            "bulletType": "simple",
            "numberOfBullets": 3,
            "turns": true,
            "piercing": false
        }
    },
    {
        "name": "sniper tower",
        "spriteSheetNum": 3,
        "displayInfo": {
            "Ammo": "standard",
            "Damage": "high",
            "Rate": "low",
            "Range": "far",
            "Resistance": "none"
        },
        "gameData": {
            "seekRange": 10,
            "shootRange": 20,
            "damage": 5,
            "rateOfFire": 240,
            "bulletSpeed": 15,
            "bulletType": "simple",
            "numberOfBullets": 1,
            "turns": true,
            "piercing": false
        }
    }
]
